kaiju_db/__init__.py
kaiju_db/functions.py
kaiju_db/services.py
kaiju_db/types.py
kaiju_db/tests/__init__.py
kaiju_db/tests/fixtures.py
kaiju_db/tests/test_db.py
kaiju_db-2.3.0.dist-info/LICENSE
kaiju_db-2.3.0.dist-info/METADATA
kaiju_db-2.3.0.dist-info/WHEEL
kaiju_db-2.3.0.dist-info/top_level.txt
kaiju_db-2.3.0.dist-info/RECORD
