Metadata-Version: 2.1
Name: kaiju_db
Version: 2.3.0
Summary: Postgresql db services and tools
Home-page: https://gitlab.com/kaiju-python/kaiju-db
Author: antonnidhoggr@me.com
Author-email: antonnidhoggr@me.com
License: Apache Software License 2.0
Classifier: Development Status :: 3 - Alpha
Classifier: License :: OSI Approved :: Apache Software License
Classifier: Programming Language :: Python :: 3
Classifier: Programming Language :: Python :: 3 :: Only
Classifier: Programming Language :: Python :: 3.11
Classifier: Programming Language :: Python :: Implementation :: CPython
Requires-Python: >=3.11
License-File: LICENSE
Requires-Dist: asyncpg>=0.30
Requires-Dist: greenlet>=3.1
Requires-Dist: sqlalchemy[asyncio]>=2.0.36
Requires-Dist: sqlalchemy-utils>=0.41
Requires-Dist: kaiju-tools<3,>=2
Provides-Extra: dev
Requires-Dist: bump2version>=1.0; extra == "dev"
Requires-Dist: pyroma>=4.1; extra == "dev"
Requires-Dist: bandit>=1.7; extra == "dev"
Requires-Dist: black>=23.11; extra == "dev"
Requires-Dist: flake8>=6.1; extra == "dev"
Requires-Dist: flake8-walrus>=1.2; extra == "dev"
Requires-Dist: pyproject-flake8>=6.1; extra == "dev"
Requires-Dist: pre-commit>=3.5; extra == "dev"
Requires-Dist: pydocstyle>=6.3; extra == "dev"
Requires-Dist: setup-cfg-fmt>=2.5; extra == "dev"
Requires-Dist: restructuredtext-lint>=1.4; extra == "dev"
Requires-Dist: tox>=4.11; extra == "dev"
Requires-Dist: virtualenv-pyenv>=0.4; extra == "dev"
Requires-Dist: pip-tools>=7.3; extra == "dev"
Requires-Dist: pyupgrade>=3.15; extra == "dev"
Requires-Dist: towncrier>=23.11; extra == "dev"
Requires-Dist: isort>=5.12.0; extra == "dev"
Requires-Dist: xenon>=0.9.1; extra == "dev"
Provides-Extra: test
Requires-Dist: pytest>=7.4; extra == "test"
Requires-Dist: pytest-asyncio>=0.21; extra == "test"
Requires-Dist: docker>=6.1.3; extra == "test"
Requires-Dist: pytest-timeout>=2.1; extra == "test"
Requires-Dist: pytest-aiohttp>=1.0.5; extra == "test"
Requires-Dist: pytest-cov>=4.1.0; extra == "test"
Provides-Extra: docs
Requires-Dist: sphinx; extra == "docs"
Requires-Dist: python_docs_theme; extra == "docs"
Provides-Extra: docker
Requires-Dist: docker>=7.1.0; extra == "docker"
